falra_run_github/__init__.py
falra_run_github/__main__.py
falra_run_github/main.py
falra_run_github-0.1.5.dist-info/METADATA
falra_run_github-0.1.5.dist-info/WHEEL
falra_run_github-0.1.5.dist-info/entry_points.txt
falra_run_github-0.1.5.dist-info/top_level.txt
falra_run_github-0.1.5.dist-info/RECORD
