Metadata-Version: 2.1
Name: falra-run-github
Version: 0.1.5
Summary: UNKNOWN
Home-page: UNKNOWN
Author: UNKNOWN
Author-email: UNKNOWN
License: UNKNOWN
Platform: UNKNOWN
Requires-Dist: aiosignal (==1.3.1)
Requires-Dist: anyio (==3.6.2)
Requires-Dist: attrs (==22.2.0)
Requires-Dist: certifi (==2022.12.7)
Requires-Dist: charset-normalizer (==3.1.0)
Requires-Dist: click (==8.1.3)
Requires-Dist: distlib (==0.3.6)
Requires-Dist: fastapi (==0.94.1)
Requires-Dist: filelock (==3.10.0)
Requires-Dist: frozenlist (==1.3.3)
Requires-Dist: grpcio (==1.49.1)
Requires-Dist: h11 (==0.14.0)
Requires-Dist: idna (==3.4)
Requires-Dist: importlib-resources (==5.12.0)
Requires-Dist: jsonschema (==4.17.3)
Requires-Dist: msgpack (==1.0.5)
Requires-Dist: numpy (==1.24.2)
Requires-Dist: pandas (==1.5.3)
Requires-Dist: pkgutil-resolve-name (==1.3.10)
Requires-Dist: platformdirs (==3.1.1)
Requires-Dist: protobuf (==4.22.1)
Requires-Dist: pydantic (==1.10.6)
Requires-Dist: pyrsistent (==0.19.3)
Requires-Dist: python-dateutil (==2.8.2)
Requires-Dist: pytz (==2022.7.1)
Requires-Dist: PyYAML (==6.0)
Requires-Dist: requests (==2.28.2)
Requires-Dist: six (==1.16.0)
Requires-Dist: sniffio (==1.3.0)
Requires-Dist: starlette (==0.26.1)
Requires-Dist: typing-extensions (==4.5.0)
Requires-Dist: urllib3 (==1.26.15)
Requires-Dist: uvicorn (==0.21.0)
Requires-Dist: virtualenv (==20.21.0)
Requires-Dist: zipp (==3.15.0)
